test/__init__.py
test/test_wait_response.py
wait_response/__init__.py
wait_response/wait_response.py
wait_response-1.0.0.dist-info/DESCRIPTION.rst
wait_response-1.0.0.dist-info/METADATA
wait_response-1.0.0.dist-info/RECORD
wait_response-1.0.0.dist-info/WHEEL
wait_response-1.0.0.dist-info/entry_points.txt
wait_response-1.0.0.dist-info/metadata.json
wait_response-1.0.0.dist-info/top_level.txt
