Metadata-Version: 2.0
Name: wait-response
Version: 1.0.0
Summary: Wait for some http response
Home-page: https://github.com/dvilela/wait_response
Author: dvilela
Author-email: denisxvilela@gmail.com
License: MIT
Keywords: http response wait-for wait functional test
Platform: UNKNOWN
Classifier: Development Status :: 3 - Alpha
Classifier: Intended Audience :: Developers
Classifier: Topic :: Software Development :: Libraries :: Python Modules
Classifier: License :: OSI Approved :: MIT License
Classifier: Programming Language :: Python :: 2.7
Classifier: Programming Language :: Python :: 3
Classifier: Programming Language :: Python :: 3.2
Classifier: Programming Language :: Python :: 3.3
Classifier: Programming Language :: Python :: 3.4
Classifier: Programming Language :: Python :: 3.5
Requires-Dist: requests
